rtl/core/Xcore_if_mdec.v
`timescale 1ns / 1ps
/*========================================FILE_HEADER=====================================
# Author:  Freddi Fu(fuyufei083x@163.com)
#
# Critical Timing: 2022-2023 -
#
# date: 2023-02-17 04:43
#
# Filename: Xcore_if_mdec.v
#
# Module Name: Xcore_if_mdec.v
#
# VERSION      LAST MODIFID    Instance Modules           DESCRIPTION
#   1.0         2023-2-17        none                this is the decode module for bpu
#                                                    it provides the simple information of an instruction
#                                                    including the type of it and its offset
#
=========================================FILE_HEADER====================================*/
`include"./rtl/include/params.v"
module Xcore_if_mdec (
//input 
    input   [`WIDTH]   i_pref_instr, //input instruction
	input              i_pc_instr_vld, //whether pc is working normally
//output
    output              o_mdec_b,
    output              o_mdec_jal,
    output              o_mdec_jalr,
    output  [`WIDTH]    o_mdec_b_ofs,
    output  [`WIDTH]    o_mdec_jal_ofs,
    output  [`WIDTH]    o_mdec_jalr_ofs,
//whether the instruction is a branch 
    output              o_mdec_instr_vld
);
//****************************************************************************************  
    // key information obtain
    wire    [6:0]   opcode = i_pref_instr[6:0];
    wire    [2:0]   funct3 = i_pref_instr[14:12];
    wire    [4:0]   rd = i_pref_instr[11:7];
    wire    [4:0]   rs1 = i_pref_instr[19:15];
//****************************************************************************************  
    wire predec_jalr = opcode==7'b1100111;
    // wire predec_ret = 1'b0;
    wire predec_b = opcode==7'b1100011;
    wire predec_jal = opcode==7'b1101111;
// offset data (32 bit) = 32-immewidth 'b0 + offset decode, i_pref_instr[31]
// is just zero
    wire [`WIDTH] predec_b_ofs = {{`LEN-12{i_pref_instr[31]}}, i_pref_instr[7], i_pref_instr[30:25], i_pref_instr[11:8], 1'b0};
    wire [`WIDTH] predec_jal_ofs = {{`LEN-20{i_pref_instr[31]}}, i_pref_instr[19:12], i_pref_instr[20], i_pref_instr[30:21], 1'b0};
    wire [`WIDTH] predec_jalr_ofs = {{`LEN-11{i_pref_instr[31]}},  i_pref_instr[30:21], 1'b0};
//****************************************************************************************  
//assignment 
    assign o_mdec_b = predec_b;
    assign o_mdec_jal = predec_jal;
    assign o_mdec_jalr = predec_jalr;
    assign o_mdec_b_ofs = predec_b_ofs;
    assign o_mdec_jal_ofs = predec_jal_ofs;
    assign o_mdec_jalr_ofs = predec_jalr_ofs;
    assign o_mdec_instr_vld = i_pc_instr_vld&(predec_b|predec_jal|predec_jalr);
endmodule

dump.vcd
$version Generated by VerilatedVcd $end
$date Fri Feb 17 23:36:04 2023 $end
$timescale 1s $end

 $scope module TOP $end
  $var wire  1 $ i_pc_instr_vld $end
  $var wire 32 # i_pref_instr [31:0] $end
  $var wire  1 % o_mdec_b $end
  $var wire 32 ( o_mdec_b_ofs [31:0] $end
  $var wire  1 + o_mdec_instr_vld $end
  $var wire  1 & o_mdec_jal $end
  $var wire 32 ) o_mdec_jal_ofs [31:0] $end
  $var wire  1 ' o_mdec_jalr $end
  $var wire 32 * o_mdec_jalr_ofs [31:0] $end
  $scope module Xcore_if_mdec $end
   $var wire  3 - funct3 [2:0] $end
   $var wire  1 $ i_pc_instr_vld $end
   $var wire 32 # i_pref_instr [31:0] $end
   $var wire  1 % o_mdec_b $end
   $var wire 32 ( o_mdec_b_ofs [31:0] $end
   $var wire  1 + o_mdec_instr_vld $end
   $var wire  1 & o_mdec_jal $end
   $var wire 32 ) o_mdec_jal_ofs [31:0] $end
   $var wire  1 ' o_mdec_jalr $end
   $var wire 32 * o_mdec_jalr_ofs [31:0] $end
   $var wire  7 , opcode [6:0] $end
   $var wire  1 % predec_b $end
   $var wire 32 ( predec_b_ofs [31:0] $end
   $var wire  1 & predec_jal $end
   $var wire 32 ) predec_jal_ofs [31:0] $end
   $var wire  1 ' predec_jalr $end
   $var wire 32 * predec_jalr_ofs [31:0] $end
   $var wire  5 . rd [4:0] $end
   $var wire  5 / rs1 [4:0] $end
  $upscope $end
 $upscope $end
$enddefinitions $end


#1
b00000000000000000000000000100100 #
1$
0%
0&
0'
b00000000000000000000000000000000 (
b00000000000000000000000000000000 )
b00000000000000000000000000000000 *
0+
b0100100 ,
b000 -
b00000 .
b00000 /
#2
b00000000000000000000001000000011 #
b00000000000000000000000000000100 (
b0000011 ,
b00100 .
#3
b00000000000000000000000000111100 #
b00000000000000000000000000000000 (
b0111100 ,
b00000 .
#4
b00000000000000000000000110111010 #
0$
b00000000000000000000100000000010 (
b0111010 ,
b00011 .
#5
b00000000000000000000001100011100 #
1$
b00000000000000000000000000000110 (
b0011100 ,
b00110 .
#6
b00000000000000000000000011111100 #
0$
b00000000000000000000100000000000 (
b1111100 ,
b00001 .
#7
b00000000000000000000000101001110 #
b00000000000000000000000000000010 (
b1001110 ,
b00010 .
#8
b00000000000000000000001100100001 #
1$
b00000000000000000000000000000110 (
b0100001 ,
b00110 .
#9
b00000000000000000000000001100101 #
0$
b00000000000000000000000000000000 (
b1100101 ,
b00000 .
#10
b00000000000000000000000010001000 #
b00000000000000000000100000000000 (
b0001000 ,
b00001 .
#11
b00000000000000000000001000011111 #
1$
b00000000000000000000000000000100 (
b0011111 ,
b00100 .
#12
b00000000000000000000001000101010 #
b0101010 ,
#13
b00000000000000000000000000000101 #
0$
b00000000000000000000000000000000 (
b0000101 ,
b00000 .
#14
b00000000000000000000001111100110 #
b00000000000000000000100000000110 (
b1100110 ,
b00111 .
#15
b00000000000000000000000101101000 #
1$
b00000000000000000000000000000010 (
b1101000 ,
b00010 .
#16
b00000000000000000000000001001101 #
b00000000000000000000000000000000 (
b1001101 ,
b00000 .
#17
b00000000000000000000001001111001 #
0$
b00000000000000000000000000000100 (
b1111001 ,
b00100 .
#18
b00000000000000000000000011110010 #
1$
b00000000000000000000100000000000 (
b1110010 ,
b00001 .
#19
b00000000000000000000001100100110 #
b00000000000000000000000000000110 (
b0100110 ,
b00110 .
#20
b00000000000000000000000010001110 #
b00000000000000000000100000000000 (
b0001110 ,
b00001 .
#21
b00000000000000000000000001100010 #
b00000000000000000000000000000000 (
b1100010 ,
b00000 .
#22
b00000000000000000000001011001111 #
b00000000000000000000100000000100 (
b1001111 ,
b00101 .
#23
b00000000000000000000001001100100 #
0$
b00000000000000000000000000000100 (
b1100100 ,
b00100 .
#24
b00000000000000000000001110000011 #
b00000000000000000000100000000110 (
b0000011 ,
b00111 .
#25
b00000000000000000000001101100110 #
1$
b00000000000000000000000000000110 (
b1100110 ,
b00110 .
#26
b00000000000000000000000001111110 #
b00000000000000000000000000000000 (
b1111110 ,
b00000 .
#27
b00000000000000000000001011011010 #
b00000000000000000000100000000100 (
b1011010 ,
b00101 .
#28
b00000000000000000000001010111010 #
0$
b0111010 ,
#29
b00000000000000000000000110100100 #
b00000000000000000000100000000010 (
b0100100 ,
b00011 .
#30
b00000000000000000000000111100001 #
b1100001 ,
#31
b00000000000000000000000110010000 #
1$
b0010000 ,
#32
b00000000000000000000000010011000 #
0$
b00000000000000000000100000000000 (
b0011000 ,
b00001 .
#33
b00000000000000000000000010000010 #
b0000010 ,
#34
b00000000000000000000001011000000 #
b00000000000000000000100000000100 (
b1000000 ,
b00101 .
#35
b00000000000000000000000000111001 #
1$
b00000000000000000000000000000000 (
b0111001 ,
b00000 .
#36
b00000000000000000000000111101111 #
0$
1&
b00000000000000000000100000000010 (
b1101111 ,
b00011 .
#37
b00000000000000000000000011011100 #
0&
b00000000000000000000100000000000 (
b1011100 ,
b00001 .
#38
b00000000000000000000001001010000 #
b00000000000000000000000000000100 (
b1010000 ,
b00100 .
#39
b00000000000000000000001010110001 #
b00000000000000000000100000000100 (
b0110001 ,
b00101 .
#40
b00000000000000000000001000001101 #
1$
b00000000000000000000000000000100 (
b0001101 ,
b00100 .
#41
b00000000000000000000000111100011 #
1%
b00000000000000000000100000000010 (
1+
b1100011 ,
b00011 .
#42
b00000000000000000000001110100000 #
0$
0%
b00000000000000000000100000000110 (
0+
b0100000 ,
b00111 .
#43
b00000000000000000000000100110101 #
b00000000000000000000000000000010 (
b0110101 ,
b00010 .
#44
b00000000000000000000001110011110 #
1$
b00000000000000000000100000000110 (
b0011110 ,
b00111 .
#45
b00000000000000000000000011111001 #
0$
b00000000000000000000100000000000 (
b1111001 ,
b00001 .
#46
b00000000000000000000000111100101 #
b00000000000000000000100000000010 (
b1100101 ,
b00011 .
#47
b00000000000000000000001110101111 #
b00000000000000000000100000000110 (
b0101111 ,
b00111 .
#48
b00000000000000000000001010010110 #
1$
b00000000000000000000100000000100 (
b0010110 ,
b00101 .
#49
b00000000000000000000000000001011 #
0$
b00000000000000000000000000000000 (
b0001011 ,
b00000 .
#50
b00000000000000000000001111011101 #
b00000000000000000000100000000110 (
b1011101 ,
b00111 .
#51
b00000000000000000000000010101010 #
1$
b00000000000000000000100000000000 (
b0101010 ,
b00001 .
