rtl/core/Xcore_if_pc.v
`timescale 1ns / 1ps
/*========================================FILE_HEADER=====================================
# Author:  Freddi Fu(fuyufei083x@163.com)
#
# Critical Timing: 2022-2023 -
#
# date: 2023-01-14 23:52
#
# Filename: Xcore_if_pc.v
#
# Module Name: Xcore_if_pc.v
#
# VERSION      LAST MODIFID    Instance Modules           DESCRIPTION
#   1.0         2022-1-15        none/dff               the program counter of the processor.
#
#  function: if there is no jump from bpu, then plus four +4 pc -> pc + 4 
#            if there should jump, then jump to the branch target from bpu pc -> branch pc
#            if there should stall, then the stall signal is high to make no new instr is fetched
#            if there should flush, then jump to the the pc provided by the flush target
#
=========================================FILE_HEADER====================================*/
`include"./rtl/include/params.v"
module Xcore_if_pc(
// clk and reset signals
    input                       i_sys_clk,
	input                       i_sys_rst,
// input instruction and bpu information
    input      [`WIDTH]         i_iram_instr,
	input                       i_bpu_redir, // taken for 1 and not taken for 0
	input      [`WIDTH]         i_bpu_target,
//	input      [1:0]            i_bpu_bits,
	input                       i_bpu_btb_err, /* if there is am error, the target may be useless and 
	we need to update the btb and get information from the cmt module to receive flush signal*/ 
// flush and jump control
    input                       i_flush_pc_req,
	input      [`WIDTH]         i_flush_pc_target,
	input                       i_if_stall,
// outputs
    output     [`WIDTH]         o_pc_addr,
	output     [`WIDTH]         o_pc_bpu_addr, // the address information given to bpu for update 
	output                      o_pc_req,
	output     [`WIDTH]         o_pc_instr,
	output                      o_pc_addr_valid,
	output                      o_pc_instr_valid
);
//****************************************************************************************  
//period counter
reg [1:0]                       period_cnt;
always@(posedge i_sys_clk or negedge i_sys_rst)
begin
	if(i_sys_rst==1'b0)
		period_cnt <= 'd0;
	else if(i_if_stall==1'b1)
		period_cnt <= period_cnt;
	else if(period_cnt==2'b11)
		period_cnt <= 'd0;
	else
		period_cnt <= period_cnt + 1'b1;
end
//****************************************************************************************  
//the fetch process
reg [`WIDTH]                   pc_addr_r;
always@(posedge i_sys_clk or negedge i_sys_rst)
begin
	if(i_sys_rst==1'b0)
		pc_addr_r <= 'd1;
	else if(i_if_stall==1'b1)
		pc_addr_r <= pc_addr_r;
	else if((period_cnt==2'b11)&&(i_flush_pc_req==1'b1))
		pc_addr_r <= i_flush_pc_target;
	else if(period_cnt == 2'b11)
		pc_addr_r <= (i_bpu_redir&(~i_bpu_btb_err)) ? i_bpu_target : (pc_addr_r + 32'd4);
	else
		pc_addr_r <= pc_addr_r;
end
//****************************************************************************************  
//enable signals
reg                           pc_valid;
reg                           instr_valid;
reg                           iram_req;
always@(posedge i_sys_clk or negedge i_sys_rst)
begin
	if(i_sys_rst==1'b0)
	begin
		pc_valid <= 'd0;
		instr_valid <= 'd0;
		iram_req <= 'd0;
	end
	else if(i_if_stall==1'b1)
	begin
		pc_valid <= 'd0;
		instr_valid <= 'd0;
		iram_req <= 'd0;
	end
	else if(period_cnt==2'b11)
	begin
		pc_valid <= 1'b1;
		iram_req <= 1'b1;
		instr_valid <= 1'b0;
	end
	else if(period_cnt==2'b00)
	begin	
		pc_valid <= 1'b0;
		iram_req <= 1'b0;
		instr_valid <= 1'b1;
	end
	else 
	begin
		pc_valid <= 'd0;
		instr_valid <= 'd0;
		iram_req <= 'd0;
	end
end
//****************************************************************************************  
//outputs
assign o_pc_req = iram_req;
assign o_pc_addr = pc_addr_r;
assign o_pc_instr = i_iram_instr;
assign o_pc_bpu_addr = pc_addr_r;
assign o_pc_addr_valid = pc_valid;
assign o_pc_instr_valid = instr_valid;

endmodule

dump.vcd
$version Generated by VerilatedVcd $end
$date Sun Jan 15 05:23:47 2023 $end
$timescale 1s $end

 $scope module TOP $end
  $var wire  1 - i_bpu_btb_err $end
  $var wire  1 + i_bpu_redir $end
  $var wire 32 , i_bpu_target [31:0] $end
  $var wire  1 . i_flush_pc_req $end
  $var wire 32 / i_flush_pc_target [31:0] $end
  $var wire  1 0 i_if_stall $end
  $var wire 32 * i_iram_instr [31:0] $end
  $var wire  1 ( i_sys_clk $end
  $var wire  1 ) i_sys_rst $end
  $var wire 32 1 o_pc_addr [31:0] $end
  $var wire  1 5 o_pc_addr_valid $end
  $var wire 32 2 o_pc_bpu_addr [31:0] $end
  $var wire 32 4 o_pc_instr [31:0] $end
  $var wire  1 6 o_pc_instr_valid $end
  $var wire  1 3 o_pc_req $end
  $scope module Xcore_if_pc $end
   $var wire  1 - i_bpu_btb_err $end
   $var wire  1 + i_bpu_redir $end
   $var wire 32 , i_bpu_target [31:0] $end
   $var wire  1 . i_flush_pc_req $end
   $var wire 32 / i_flush_pc_target [31:0] $end
   $var wire  1 0 i_if_stall $end
   $var wire 32 * i_iram_instr [31:0] $end
   $var wire  1 ( i_sys_clk $end
   $var wire  1 ) i_sys_rst $end
   $var wire  1 & instr_valid $end
   $var wire  1 ' iram_req $end
   $var wire 32 1 o_pc_addr [31:0] $end
   $var wire  1 5 o_pc_addr_valid $end
   $var wire 32 1 o_pc_bpu_addr [31:0] $end
   $var wire 32 4 o_pc_instr [31:0] $end
   $var wire  1 6 o_pc_instr_valid $end
   $var wire  1 3 o_pc_req $end
   $var wire 32 $ pc_addr_r [31:0] $end
   $var wire  1 % pc_valid $end
   $var wire  2 # period_cnt [1:0] $end
  $upscope $end
 $upscope $end
$enddefinitions $end


#1
b00 #
b00000000000000000000000000000000 $
0%
0&
0'
0(
0)
b00000000000000000000000000000000 *
0+
b00000000000000000000000000000000 ,
0-
0.
b00000000000000000000000000000000 /
00
b00000000000000000000000000000000 1
b00000000000000000000000000000000 2
03
b00000000000000000000000000000000 4
05
06
#2
b00000000000000000000000000000001 $
1(
b00000000000000000000000000000001 1
b00000000000000000000000000000001 2
#3
0(
#4
1(
#5
0(
#6
1(
#7
0(
#8
1(
#9
0(
#10
1(
#11
0(
#12
1(
#13
0(
#14
1(
#15
0(
#16
1(
#17
0(
#18
1(
#19
0(
#20
1(
#21
0(
1)
b00000000000000000000000101001101 *
b00000000000000000000001110000110 ,
1-
b00000000000000000000000101001101 4
#22
b01 #
1&
1(
16
#23
0(
b00000000000000000000001101100100 *
1+
b00000000000000000000000011010011 ,
0-
b00000000000000000000001101100100 4
#24
b10 #
0&
1(
06
#25
0(
b00000000000000000000000111011010 *
b00000000000000000000000110110101 ,
1-
b00000000000000000000000111011010 4
#26
b11 #
1(
#27
0(
b00000000000000000000000010001100 *
b00000000000000000000000011010101 ,
0-
b00000000000000000000000010001100 4
#28
b00 #
b00000000000000000000000011010101 $
1%
1'
1(
b00000000000000000000000011010101 1
b00000000000000000000000011010101 2
13
15
#29
0(
b00000000000000000000000111010001 *
0+
b00000000000000000000000101110100 ,
b00000000000000000000000111010001 4
#30
b01 #
0%
1&
0'
1(
03
05
16
#31
0(
b00000000000000000000000110110100 *
b00000000000000000000001011001101 ,
1-
b00000000000000000000000110110100 4
#32
b10 #
0&
1(
06
#33
0(
b00000000000000000000000100110011 *
b00000000000000000000001011111010 ,
b00000000000000000000000100110011 4
#34
b11 #
1(
#35
0(
b00000000000000000000001011111111 *
1+
b00000000000000000000001011110010 ,
0-
b00000000000000000000001011111111 4
#36
b00 #
b00000000000000000000001011110010 $
1%
1'
1(
b00000000000000000000001011110010 1
b00000000000000000000001011110010 2
13
15
#37
0(
b00000000000000000000000110001101 *
0+
b00000000000000000000001001010010 ,
1-
b00000000000000000000000110001101 4
#38
b01 #
0%
1&
0'
1(
03
05
16
#39
0(
b00000000000000000000001010110101 *
b00000000000000000000001010101110 ,
0-
b00000000000000000000001010110101 4
#40
b10 #
0&
1(
06
#41
0(
b00000000000000000000001001000011 *
1+
b00000000000000000000000110001100 ,
1-
b00000000000000000000001001000011 4
#42
b11 #
1(
#43
0(
b00000000000000000000000110110010 *
b00000000000000000000000111110010 ,
0-
b00000000000000000000000110110010 4
#44
b00 #
b00000000000000000000000111110010 $
1%
1'
1(
b00000000000000000000000111110010 1
b00000000000000000000000111110010 2
13
15
#45
0(
b00000000000000000000001011001011 *
0+
b00000000000000000000000000001101 ,
b00000000000000000000001011001011 4
#46
b01 #
0%
1&
0'
1(
03
05
16
#47
0(
b00000000000000000000000110000111 *
b00000000000000000000001010101001 ,
1-
b00000000000000000000000110000111 4
#48
b10 #
0&
1(
06
#49
0(
b00000000000000000000001011100001 *
b00000000000000000000001010011111 ,
b00000000000000000000001011100001 4
#50
b11 #
1(
#51
0(
b00000000000000000000001100001100 *
1+
b00000000000000000000001000101111 ,
b00000000000000000000001100001100 4
#52
b00 #
b00000000000000000000000111110110 $
1%
1'
1(
b00000000000000000000000111110110 1
b00000000000000000000000111110110 2
13
15
#53
0(
b00000000000000000000000000001011 *
b00000000000000000000000110001100 ,
b00000000000000000000000000001011 4
#54
b01 #
0%
1&
0'
1(
03
05
16
#55
0(
b00000000000000000000001110101010 *
b00000000000000000000001101010001 ,
b00000000000000000000001110101010 4
#56
b10 #
0&
1(
06
#57
0(
b00000000000000000000000010011101 *
b00000000000000000000000010111101 ,
b00000000000000000000000010011101 4
#58
b11 #
1(
#59
0(
b00000000000000000000001101000010 *
0+
b00000000000000000000000111010100 ,
0-
b00000000000000000000001101000010 4
#60
b00 #
b00000000000000000000000111111010 $
1%
1'
1(
b00000000000000000000000111111010 1
b00000000000000000000000111111010 2
13
15
#61
0(
b00000000000000000000001000011001 *
b00000000000000000000001010001011 ,
b00000000000000000000001000011001 4
#62
b01 #
0%
1&
0'
1(
03
05
16
#63
0(
b00000000000000000000000010111100 *
b00000000000000000000001001011011 ,
1-
b00000000000000000000000010111100 4
#64
b10 #
0&
1(
06
#65
0(
b00000000000000000000001011011001 *
1+
b00000000000000000000000101111110 ,
0-
b00000000000000000000001011011001 4
#66
b11 #
1(
#67
0(
b00000000000000000000001010001011 *
0+
b00000000000000000000001001111111 ,
b00000000000000000000001010001011 4
#68
b00 #
b00000000000000000000000111111110 $
1%
1'
1(
b00000000000000000000000111111110 1
b00000000000000000000000111111110 2
13
15
#69
0(
b00000000000000000000000000110011 *
b00000000000000000000000101011000 ,
1-
b00000000000000000000000000110011 4
#70
b01 #
0%
1&
0'
1(
03
05
16
#71
0(
b00000000000000000000000001000110 *
b00000000000000000000000111001011 ,
0-
b00000000000000000000000001000110 4
#72
b10 #
0&
1(
06
#73
0(
b00000000000000000000000110001000 *
1+
b00000000000000000000001100110110 ,
b00000000000000000000000110001000 4
#74
b11 #
1(
#75
0(
b00000000000000000000000100111101 *
0+
b00000000000000000000001011010111 ,
b00000000000000000000000100111101 4
#76
b00 #
b00000000000000000000001000000010 $
1%
1'
1(
b00000000000000000000001000000010 1
b00000000000000000000001000000010 2
13
15
#77
0(
b00000000000000000000001011101111 *
b00000000000000000000001011111001 ,
1-
b00000000000000000000001011101111 4
#78
b01 #
0%
1&
0'
1(
03
05
16
#79
0(
b00000000000000000000001010011001 *
1+
b00000000000000000000001101001100 ,
b00000000000000000000001010011001 4
#80
b10 #
0&
1(
06
#81
0(
b00000000000000000000001001001110 *
b00000000000000000000001101011000 ,
b00000000000000000000001001001110 4
#82
b11 #
1(
#83
0(
b00000000000000000000000001111010 *
b00000000000000000000001101110001 ,
b00000000000000000000000001111010 4
#84
b00 #
b00000000000000000000001000000110 $
1%
1'
1(
b00000000000000000000001000000110 1
b00000000000000000000001000000110 2
13
15
#85
0(
b00000000000000000000000111100100 *
b00000000000000000000000010001110 ,
0-
b00000000000000000000000111100100 4
#86
b01 #
0%
1&
0'
1(
03
05
16
#87
0(
b00000000000000000000000101110100 *
b00000000000000000000001100010010 ,
1-
b00000000000000000000000101110100 4
#88
b10 #
0&
1(
06
#89
0(
b00000000000000000000000011100111 *
b00000000000000000000001111001001 ,
0-
b00000000000000000000000011100111 4
#90
b11 #
1(
#91
0(
b00000000000000000000001101010101 *
b00000000000000000000000101111110 ,
1-
b00000000000000000000001101010101 4
#92
b00 #
b00000000000000000000001000001010 $
1%
1'
1(
b00000000000000000000001000001010 1
b00000000000000000000001000001010 2
13
15
#93
0(
b00000000000000000000000000000011 *
b00000000000000000000000111101111 ,
0-
b00000000000000000000000000000011 4
#94
b01 #
0%
1&
0'
1(
03
05
16
#95
0(
b00000000000000000000000111001010 *
b00000000000000000000000000001111 ,
1-
b00000000000000000000000111001010 4
#96
b10 #
0&
1(
06
#97
0(
b00000000000000000000001000001001 *
b00000000000000000000000011110011 ,
b00000000000000000000001000001001 4
#98
b11 #
1(
#99
0(
b00000000000000000000000101000001 *
b00000000000000000000001100110101 ,
b00000000000000000000000101000001 4
#100
b00 #
b00000000000000000000001000001110 $
1%
1'
1(
b00000000000000000000001000001110 1
b00000000000000000000001000001110 2
13
15
#101
0(
b00000000000000000000000100110000 *
0+
b00000000000000000000000101010011 ,
0-
b00000000000000000000000100110000 4
#102
b01 #
0%
1&
0'
1(
03
05
16
#103
0(
b00000000000000000000001000011101 *
b00000000000000000000000110100010 ,
b00000000000000000000001000011101 4
#104
b10 #
0&
1(
06
#105
0(
b00000000000000000000001010101100 *
b00000000000000000000000100101011 ,
b00000000000000000000001010101100 4
#106
b11 #
1(
#107
0(
b00000000000000000000000000001100 *
b00000000000000000000000001000100 ,
1-
b00000000000000000000000000001100 4
#108
b00 #
b00000000000000000000001000010010 $
1%
1'
1(
b00000000000000000000001000010010 1
b00000000000000000000001000010010 2
13
15
#109
0(
b00000000000000000000001100100010 *
1+
b00000000000000000000001010101100 ,
0-
b00000000000000000000001100100010 4
#110
b01 #
0%
1&
0'
1(
03
05
16
#111
0(
b00000000000000000000001101110010 *
b00000000000000000000000100000110 ,
b00000000000000000000001101110010 4
#112
b10 #
0&
1(
06
#113
0(
b00000000000000000000001000100110 *
b00000000000000000000010000000000 ,
1-
b00000000000000000000001000100110 4
#114
b11 #
1(
#115
0(
b00000000000000000000001001100000 *
b00000000000000000000001010001110 ,
b00000000000000000000001001100000 4
#116
b00 #
b00000000000000000000001000010110 $
1%
1'
1(
b00000000000000000000001000010110 1
b00000000000000000000001000010110 2
13
15
#117
0(
b00000000000000000000001011111000 *
b00000000000000000000001000111000 ,
0-
b00000000000000000000001011111000 4
#118
b01 #
0%
1&
0'
1(
03
05
16
#119
0(
b00000000000000000000000001000100 *
b00000000000000000000000000011100 ,
1-
b00000000000000000000000001000100 4
#120
b10 #
0&
1(
06
#121
0(
b00000000000000000000000101000110 *
0+
b00000000000000000000000011110011 ,
b00000000000000000000000101000110 4
#122
b11 #
1(
#123
0(
b00000000000000000000001111110101 *
b00000000000000000000000101100100 ,
0-
b00000000000000000000000000010010 /
b00000000000000000000001111110101 4
#124
b00 #
b00000000000000000000001000011010 $
1%
1'
1(
b00000000000000000000001000011010 1
b00000000000000000000001000011010 2
13
15
#125
0(
b00000000000000000000000000000011 *
b00000000000000000000001011001111 ,
1-
1.
b00000000000000000000000011110110 /
b00000000000000000000000000000011 4
#126
b01 #
0%
1&
0'
1(
03
05
16
#127
0(
b00000000000000000000001100000110 *
1+
b00000000000000000000000001011111 ,
0.
b00000000000000000000001011101101 /
b00000000000000000000001100000110 4
#128
b10 #
0&
1(
06
#129
0(
b00000000000000000000000011110111 *
b00000000000000000000001011001111 ,
0-
1.
b00000000000000000000001100010101 /
b00000000000000000000000011110111 4
#130
b11 #
1(
#131
0(
b00000000000000000000001100001011 *
0+
b00000000000000000000001000000111 ,
0.
b00000000000000000000001011111100 /
b00000000000000000000001100001011 4
#132
b00 #
b00000000000000000000001000011110 $
1%
1'
1(
b00000000000000000000001000011110 1
b00000000000000000000001000011110 2
13
15
#133
0(
b00000000000000000000000110100110 *
1+
b00000000000000000000000000110111 ,
b00000000000000000000001110101000 /
b00000000000000000000000110100110 4
#134
b01 #
0%
1&
0'
1(
03
05
16
#135
0(
b00000000000000000000001100011101 *
0+
b00000000000000000000001010001001 ,
1-
b00000000000000000000001011100111 /
b00000000000000000000001100011101 4
#136
b10 #
0&
1(
06
#137
0(
b00000000000000000000001011100100 *
b00000000000000000000001101000100 ,
0-
1.
b00000000000000000000001011010110 /
b00000000000000000000001011100100 4
#138
b11 #
1(
#139
0(
b00000000000000000000001000110001 *
b00000000000000000000000101100001 ,
1-
0.
b00000000000000000000000100000101 /
b00000000000000000000001000110001 4
#140
b00 #
b00000000000000000000001000100010 $
1%
1'
1(
b00000000000000000000001000100010 1
b00000000000000000000001000100010 2
13
15
#141
0(
b00000000000000000000000000010011 *
b00000000000000000000000011000101 ,
b00000000000000000000000111010010 /
b00000000000000000000000000010011 4
#142
b01 #
0%
1&
0'
1(
03
05
16
#143
0(
b00000000000000000000000100011010 *
b00000000000000000000001011010100 ,
b00000000000000000000001011101101 /
b00000000000000000000000100011010 4
#144
b10 #
0&
1(
06
#145
0(
b00000000000000000000000011111010 *
b00000000000000000000001100001001 ,
1.
b00000000000000000000000000110010 /
b00000000000000000000000011111010 4
#146
b11 #
1(
#147
0(
b00000000000000000000001001101010 *
1+
b00000000000000000000000001100010 ,
b00000000000000000000000111111001 /
b00000000000000000000001001101010 4
#148
b00 #
b00000000000000000000000111111001 $
1%
1'
1(
b00000000000000000000000111111001 1
b00000000000000000000000111111001 2
13
15
#149
0(
b00000000000000000000000010000101 *
0+
b00000000000000000000000010000111 ,
b00000000000000000000001001000101 /
b00000000000000000000000010000101 4
#150
b01 #
0%
1&
0'
1(
03
05
16
#151
0(
b00000000000000000000001011101101 *
b00000000000000000000001100010000 ,
b00000000000000000000000000101011 /
b00000000000000000000001011101101 4
#152
b10 #
0&
1(
06
#153
0(
b00000000000000000000000110000110 *
1+
b00000000000000000000001011101111 ,
0-
0.
b00000000000000000000000010111110 /
b00000000000000000000000110000110 4
#154
b11 #
1(
#155
0(
b00000000000000000000001101001000 *
0+
b00000000000000000000000110101010 ,
b00000000000000000000000010000100 /
b00000000000000000000001101001000 4
#156
b00 #
b00000000000000000000000111111101 $
1%
1'
1(
b00000000000000000000000111111101 1
b00000000000000000000000111111101 2
13
15
#157
0(
b00000000000000000000001010000101 *
b00000000000000000000001001000011 ,
1.
b00000000000000000000001101000101 /
b00000000000000000000001010000101 4
#158
b01 #
0%
1&
0'
1(
03
05
16
#159
0(
b00000000000000000000000011011111 *
b00000000000000000000001001111010 ,
1-
0.
b00000000000000000000001010101101 /
b00000000000000000000000011011111 4
#160
b10 #
0&
1(
06
#161
0(
b00000000000000000000001110101110 *
1+
b00000000000000000000001011110100 ,
1.
b00000000000000000000000101011011 /
b00000000000000000000001110101110 4
#162
b11 #
1(
#163
0(
b00000000000000000000001011101010 *
b00000000000000000000000011011011 ,
b00000000000000000000000110101101 /
b00000000000000000000001011101010 4
#164
b00 #
b00000000000000000000000110101101 $
1%
1'
1(
b00000000000000000000000110101101 1
b00000000000000000000000110101101 2
13
15
#165
0(
b00000000000000000000001010011000 *
b00000000000000000000001101111010 ,
b00000000000000000000000011001011 /
b00000000000000000000001010011000 4
#166
b01 #
0%
1&
0'
1(
03
05
16
#167
0(
b00000000000000000000000011001010 *
0+
b00000000000000000000000010000110 ,
0-
0.
b00000000000000000000000111110011 /
b00000000000000000000000011001010 4
#168
b10 #
0&
1(
06
#169
0(
b00000000000000000000001001010101 *
1+
b00000000000000000000001111100100 ,
1-
b00000000000000000000001110111111 /
b00000000000000000000001001010101 4
#170
b11 #
1(
#171
0(
b00000000000000000000001101111100 *
0+
b00000000000000000000001010000111 ,
0-
1.
b00000000000000000000000100000100 /
b00000000000000000000001101111100 4
#172
b00 #
b00000000000000000000000100000100 $
1%
1'
1(
b00000000000000000000000100000100 1
b00000000000000000000000100000100 2
13
15
#173
0(
b00000000000000000000001111001100 *
1+
b00000000000000000000000100001001 ,
0.
b00000000000000000000000101101011 /
b00000000000000000000001111001100 4
#174
b01 #
0%
1&
0'
1(
03
05
16
#175
0(
b00000000000000000000001001010110 *
0+
b00000000000000000000000100010010 ,
1.
b00000000000000000000001100001101 /
b00000000000000000000001001010110 4
#176
b10 #
0&
1(
06
#177
0(
b00000000000000000000001010011101 *
b00000000000000000000001110001011 ,
1-
0.
b00000000000000000000001011110010 /
b00000000000000000000001010011101 4
#178
b11 #
1(
#179
0(
b00000000000000000000000100010111 *
1+
b00000000000000000000001100110111 ,
0-
b00000000000000000000000011100110 /
b00000000000000000000000100010111 4
#180
b00 #
b00000000000000000000001100110111 $
1%
1'
1(
b00000000000000000000001100110111 1
b00000000000000000000001100110111 2
13
15
#181
0(
b00000000000000000000000010111001 *
0+
b00000000000000000000001001000011 ,
1.
b00000000000000000000001001011101 /
b00000000000000000000000010111001 4
#182
b01 #
0%
1&
0'
1(
03
05
16
#183
0(
b00000000000000000000000001000111 *
1+
b00000000000000000000000101100010 ,
1-
0.
b00000000000000000000000000000000 /
10
b00000000000000000000000001000111 4
#184
0&
1(
06
#185
0(
b00000000000000000000001001000011 *
0+
b00000000000000000000001101110100 ,
0-
00
b00000000000000000000001001000011 4
#186
b10 #
1(
#187
0(
b00000000000000000000000101000111 *
b00000000000000000000001011011110 ,
1-
b00000000000000000000000101000111 4
#188
b11 #
1(
#189
0(
b00000000000000000000001001101010 *
b00000000000000000000000110011110 ,
0-
b00000000000000000000001001101010 4
#190
b00 #
b00000000000000000000001100111011 $
1%
1'
1(
b00000000000000000000001100111011 1
b00000000000000000000001100111011 2
13
15
#191
0(
b00000000000000000000001110001100 *
b00000000000000000000000100011110 ,
10
b00000000000000000000001110001100 4
#192
0%
0'
1(
03
05
#193
0(
b00000000000000000000000111011001 *
1+
b00000000000000000000001110111110 ,
1-
00
b00000000000000000000000111011001 4
#194
b01 #
1&
1(
16
#195
0(
b00000000000000000000001000011100 *
0+
b00000000000000000000000110100001 ,
0-
b00000000000000000000001000011100 4
#196
b10 #
0&
1(
06
#197
0(
b00000000000000000000001011000000 *
b00000000000000000000000101110011 ,
10
b00000000000000000000001011000000 4
#198
1(
#199
0(
b00000000000000000000000101000100 *
b00000000000000000000000011111101 ,
1-
b00000000000000000000000101000100 4
#200
1(
#201
0(
b00000000000000000000001100000100 *
1+
b00000000000000000000001001101001 ,
0-
b00000000000000000000001100000100 4
#202
1(
#203
0(
b00000000000000000000001010001100 *
0+
b00000000000000000000000001111101 ,
b00000000000000000000001010001100 4
#204
1(
#205
0(
b00000000000000000000000111111000 *
b00000000000000000000001011111000 ,
b00000000000000000000000111111000 4
#206
1(
#207
0(
b00000000000000000000000000100011 *
b00000000000000000000000000000011 ,
1-
00
b00000000000000000000000000100011 4
#208
b11 #
1(
#209
0(
b00000000000000000000001010111010 *
b00000000000000000000000100010101 ,
0-
10
b00000000000000000000001010111010 4
#210
1(
#211
0(
b00000000000000000000000010010101 *
1+
b00000000000000000000001000110100 ,
00
b00000000000000000000000010010101 4
#212
b00 #
b00000000000000000000001000110100 $
1%
1'
1(
b00000000000000000000001000110100 1
b00000000000000000000001000110100 2
13
15
#213
0(
b00000000000000000000000110010011 *
0+
b00000000000000000000000000011111 ,
1-
b00000000000000000000000110010011 4
#214
b01 #
0%
1&
0'
1(
03
05
16
#215
0(
b00000000000000000000000000001001 *
1+
b00000000000000000000000101101000 ,
0-
10
b00000000000000000000000000001001 4
#216
0&
1(
06
#217
0(
b00000000000000000000001111100000 *
b00000000000000000000001110111000 ,
b00000000000000000000001111100000 4
#218
1(
#219
0(
b00000000000000000000001001010111 *
0+
b00000000000000000000000000001010 ,
1-
b00000000000000000000001001010111 4
#220
1(
#221
0(
b00000000000000000000001101011100 *
1+
b00000000000000000000000101000101 ,
0-
b00000000000000000000001101011100 4
